glvm/__init__.py
glvm-0.0.1.dist-info/LICENSE
glvm-0.0.1.dist-info/METADATA
glvm-0.0.1.dist-info/WHEEL
glvm-0.0.1.dist-info/top_level.txt
glvm-0.0.1.dist-info/RECORD
