Metadata-Version: 2.1
Name: glvm
Version: 0.0.1
Summary: generative latent variable models
Home-page: https://github.com/zhangdongkun98/generative-latent-variable-models
Author: Zhang Dongkun
Author-email: zhangdongkun98@gmail.com
License: UNKNOWN
Platform: UNKNOWN
Requires-Dist: rllib
